# Synchronized及其实现原理


## 1.Synchronized的基本使用
Synchronized是Java中解决并发问题最常用的方法。Synchronized能确保线程互斥的访问同步代码。从语法上讲，Synchronized总共有三种用法：
- 修饰普通方法
- 修饰静态方法
- 修饰代码块

```java
public class SynchronizedTest {
    public synchronized void method1(){
        //逻辑代码...
    }
    
    public static synchronized void method2(){
        //逻辑代码...
    }
    
    public void method3(){
        synchronized (this) {
            //逻辑代码...
        }
    }
}

```
## 2.Synchronized的原理
我们先通过反编译下面的代码来看看Synchronized是如何实现对代码块进行同步的：
```java
public class SynchronizedDemo {
    public void method() {
        synchronized (this) {
            System.out.println("Method 1 start");
        }
    }
}
```
通过 javap -c SynchronizedDemo 会得到如下代码：
```java
  public void method();
    Code:
       0: aload_0
       1: dup
       2: astore_1
       3: monitorenter
       4: getstatic     #6                  // Field java/lang/System.out:Ljava/io/PrintStream;
       7: ldc           #7                  // String Method 1 start
       9: invokevirtual #8                  // Method java/io/PrintStream.println:(Ljava/lang/String;)V
      12: aload_1
      13: monitorexit
      14: goto          22
      17: astore_2
      18: aload_1
      19: monitorexit
      20: aload_2
      21: athrow
      22: return
```
发现其中有两个指令**monitorenter**和**monitorexit**，
通过查看JVM的规范可知大意如下：
> 每个**对象**有一个监视器锁（**monitor**）。当monitor被占用时就会处于**锁定状态**，线程执行monitorenter指令时尝试获取monitor的所有权，过程如下：
> - 1、如果monitor的进入数为0，则该线程进入monitor，然后将进入数设置为1，该线程即为monitor的所有者。
> - 2、如果线程已经占有该monitor，只是重新进入，则进入monitor的进入数加1.
> - 3.如果其他线程已经占用了monitor，则该线程进入阻塞状态，直到monitor的进入数为0，再重新尝试获取monitor的所有权。

monitorexit：　
> - 执行monitorexit的线程必须是objectref所对应的monitor**所有者**。
> - 指令执行时，monitor的进入数减1，如果减1后进入数为0，那线程退出monitor，不再是这个monitor的所有者。其他被这个monitor阻塞的线程可以尝试去获取这个 monitor 的所有权。 

通过这两段描述，我们应该能很清楚的看出Synchronized的实现原理，Synchronized的语义底层是通过一个monitor的对象来完成，其实wait/notify等方法也依赖于monitor对象，这就是为什么只有在同步的块或者方法中才能调用wait/notify等方法，否则会抛出java.lang.IllegalMonitorStateException的异常的原因。

## 3.运行结果解释
> 面试官通常会问这样一个问题：一个对象中有两个方法，都是synchronized的，现在一个线程A进入方法1执行。那么另一个线程B能否执行方法2？答案是**不能**。

通过上面查询的JVM规范可知：对于代码块的同步实质上需要获取synchronized关键的**对象的monitor**，而方法1和方法2又是通过同一的对象去调用的，所以进入同步块之前需要去竞争同一个对象上的锁，因此只能顺序执行同步块。